my_project4_yosafe_fesaha/__init__.py
my_project4_yosafe_fesaha/yosafe_models.py
my_project4_yosafe_fesaha-0.1.0.dist-info/METADATA
my_project4_yosafe_fesaha-0.1.0.dist-info/WHEEL
my_project4_yosafe_fesaha-0.1.0.dist-info/RECORD
