Metadata-Version: 2.1
Name: my_project4_yosafe_fesaha
Version: 0.1.0
Summary: 
Author: Y581515
Author-email: yfessaha@gmail.com
Requires-Python: >=3.12,<4.0
Classifier: Programming Language :: Python :: 3
Classifier: Programming Language :: Python :: 3.12
Requires-Dist: requests (>=2.32.3,<3.0.0)
